django_redis_sentinel_plugin/__init__.py
django_redis_sentinel_plugin/cache.py
django_redis_sentinel_plugin/client/__init__.py
django_redis_sentinel_plugin/client/sentinel.py
django_redis_sentinel_plugin/pool.py
django_redis_sentinel_plugin-1.0.0.dist-info/WHEEL
django_redis_sentinel_plugin-1.0.0.dist-info/METADATA
django_redis_sentinel_plugin-1.0.0.dist-info/RECORD
